data_science_kit/__init__.py
data_science_kit/__version__.py
data_science_kit/data_science_kit.py
data_science_kit-0.0.1.dist-info/METADATA
data_science_kit-0.0.1.dist-info/WHEEL
data_science_kit-0.0.1.dist-info/top_level.txt
data_science_kit-0.0.1.dist-info/RECORD
