Metadata-Version: 2.1
Name: data-science-kit
Version: 0.0.1
Summary: Data Science Basic Functions
Home-page: https://github.com/KeremDlkmn/data-science-kit
Author: Kerem Delikmen
License: MIT
Project-URL: Source, https://github.com/KeremDlkmn/data-science-kit
Keywords: data science,data,data kit,data science kit,science,science kit,data engineer,data engineering,exploratory data analysis,eda,measurement units,data operations,data preprocessing,preprocessing
Platform: UNKNOWN
Classifier: Intended Audience :: Developers
Classifier: License :: OSI Approved :: MIT License
Classifier: Natural Language :: English
Classifier: Operating System :: OS Independent
Classifier: Programming Language :: Python :: 3
Classifier: Programming Language :: Python :: 3.6
Classifier: Programming Language :: Python :: 3.7
Classifier: Programming Language :: Python :: 3.8
Classifier: Topic :: Internet :: WWW/HTTP
Classifier: Topic :: Scientific/Engineering :: Information Analysis
Requires-Python: >=3.6
Requires-Dist: pandas (==1.0.1)
Requires-Dist: scipy (==1.1.0)
Requires-Dist: sklearn (==0.0)
Requires-Dist: ycimpute (==0.2)
Requires-Dist: numpy (==1.19.5)
Requires-Dist: researchpy (==0.3.2)
